mrx_link_git/__init__.py
mrx_link_git/_version.py
mrx_link_git/git.py
mrx_link_git/handlers.py
mrx_link_git/log.py
mrx_link_git/drivers/__init__.py
mrx_link_git/drivers/common.cpython-310-darwin.so
mrx_link_git/drivers/diff_ipynb.cpython-310-darwin.so
mrx_link_git/drivers/merge_ipynb.cpython-310-darwin.so
mrx_link_git/labextension/package.json
mrx_link_git/labextension/schemas/mrx_link_git/package.json.orig
mrx_link_git/labextension/schemas/mrx_link_git/plugin.json
mrx_link_git/labextension/static/129.1fab57f2fc95a20993bc.js
mrx_link_git/labextension/static/189.575c65a5a69efd531586.js
mrx_link_git/labextension/static/201.3693bff62428b1ae253a.js
mrx_link_git/labextension/static/213.c7029bcb5d1f51b45bb8.js
mrx_link_git/labextension/static/213.c7029bcb5d1f51b45bb8.js.LICENSE.txt
mrx_link_git/labextension/static/237.1e9884357de6fe5240b2.js
mrx_link_git/labextension/static/246.f52c4af8524aef0958cb.js
mrx_link_git/labextension/static/371.cfda8d3b05747d018d61.js
mrx_link_git/labextension/static/407.75a74b89a5bb76ee7a68.js
mrx_link_git/labextension/static/456.74019a6e72cf1e3fa9c8.js
mrx_link_git/labextension/static/514.9e5f8811bb34cf750d14.js
mrx_link_git/labextension/static/514.9e5f8811bb34cf750d14.js.LICENSE.txt
mrx_link_git/labextension/static/58.909f3f34e2df27124204.js
mrx_link_git/labextension/static/591.5ad1d0af875b99e497c0.js
mrx_link_git/labextension/static/624.e3639e8db2670e98a991.js
mrx_link_git/labextension/static/668.dede59f29ee562b8bab9.js
mrx_link_git/labextension/static/693.888cdafc297dc9f3fa2f.js
mrx_link_git/labextension/static/713.cfe0686e7f076bd50daf.js
mrx_link_git/labextension/static/728.ec3d7cbdf42baa4266df.js
mrx_link_git/labextension/static/736.ed7fa875113a4c16e32b.js
mrx_link_git/labextension/static/746.9c9a99e350b71e97925d.js
mrx_link_git/labextension/static/752.17711f62a13117a9546c.js
mrx_link_git/labextension/static/848.be2ef00bfd250b5745dc.js
mrx_link_git/labextension/static/848.be2ef00bfd250b5745dc.js.LICENSE.txt
mrx_link_git-2.2.0.dist-info/LICENSE
mrx_link_git-2.2.0.dist-info/METADATA
mrx_link_git-2.2.0.dist-info/WHEEL
mrx_link_git-2.2.0.dist-info/top_level.txt
mrx_link_git-2.2.0.dist-info/RECORD
