Metadata-Version: 2.2
Name: mrx_link_git
Version: 2.2.0
Summary: A Link™ extension for version control using Git.
Author-email: makinarocks <mrx.dev@makinarocks.ai>
License: proprietary
Project-URL: homepage, https://link.makinarocks.ai
Keywords: Jupyter,JupyterLab,JupyterLab4
Platform: Linux
Platform: Mac OS X
Platform: Windows
Classifier: License :: Other/Proprietary License
Classifier: Programming Language :: Python
Classifier: Programming Language :: Python :: 3
Classifier: Programming Language :: Python :: 3.8
Classifier: Programming Language :: Python :: 3.9
Classifier: Programming Language :: Python :: 3.10
Classifier: Programming Language :: Python :: 3.11
Classifier: Framework :: Jupyter
Classifier: Framework :: Jupyter :: JupyterLab :: 4
Classifier: Framework :: Jupyter :: JupyterLab :: Extensions :: Prebuilt
Requires-Python: >=3.8
License-File: LICENSE
Requires-Dist: apispec>=6.6
Requires-Dist: apispec-webframeworks>=1.1
Requires-Dist: jsondiff>=2.0.0
Requires-Dist: jupyter-server<3,>=2.4.0
Requires-Dist: jupyterlab<4.3,>=4.2
Requires-Dist: marshmallow>=3.21
Requires-Dist: nbdime<4.1,>=4.0
Requires-Dist: pexpect>=4.7
Requires-Dist: pyzmq>=17
Requires-Dist: swagger-ui-py>=23.9
Provides-Extra: dev
Requires-Dist: black<=22.12,>=19.3b0; extra == "dev"
Requires-Dist: build>=0.7; extra == "dev"
Requires-Dist: Cython>=3.0; extra == "dev"
Requires-Dist: deepdiff>=7.0; extra == "dev"
Requires-Dist: flake8>=3.9; extra == "dev"
Requires-Dist: isort>=5.7; extra == "dev"
Requires-Dist: mypy>=0.910; extra == "dev"
Requires-Dist: packaging>=23.1; extra == "dev"
Requires-Dist: pre-commit>=2.13; extra == "dev"
Requires-Dist: pylint>=2.9; extra == "dev"
Requires-Dist: pytest-cov>=2.12; extra == "dev"
Requires-Dist: pytest-jupyter[server]>=0.6.0; extra == "dev"
Requires-Dist: pytest-mock>=3.6; extra == "dev"
Requires-Dist: pytest-tornasync; extra == "dev"
Requires-Dist: pytest>=6.2; extra == "dev"
Requires-Dist: setuptools<77.0,>=68.0; extra == "dev"
Requires-Dist: tomli>=2.0.1; python_version < "3.11" and extra == "dev"
Requires-Dist: wheel>=0.37; extra == "dev"
